h5tiff/__init__.py
h5tiff/h5tiff.py
h5tiff-0.3.7.dist-info/LICENSE
h5tiff-0.3.7.dist-info/METADATA
h5tiff-0.3.7.dist-info/WHEEL
h5tiff-0.3.7.dist-info/top_level.txt
h5tiff-0.3.7.dist-info/RECORD
